{
  "schema_version": 1,
  "generated_at": "2026-03-20T20:30:07.372318+00:00",
  "plc_path": "192.168.140.13",
  "program_name": "Camera",
  "main_routine_name": "CameraControl",
  "main_routine_name_source": "single_routine",
  "routines": [
    "CameraControl"
  ],
  "subroutines": [],
  "udts": [
    {
      "name": "CONTROL",
      "fields": [
        {
          "name": "LEN",
          "tag_type": "atomic",
          "data_type_name": "DINT",
          "offset": 4
        },
        {
          "name": "POS",
          "tag_type": "atomic",
          "data_type_name": "DINT",
          "offset": 8
        },
        {
          "name": "EN",
          "tag_type": "atomic",
          "data_type_name": "BOOL",
          "bit": 7,
          "offset": 3
        },
        {
          "name": "EU",
          "tag_type": "atomic",
          "data_type_name": "BOOL",
          "bit": 6,
          "offset": 3
        },
        {
          "name": "DN",
          "tag_type": "atomic",
          "data_type_name": "BOOL",
          "bit": 5,
          "offset": 3
        },
        {
          "name": "EM",
          "tag_type": "atomic",
          "data_type_name": "BOOL",
          "bit": 4,
          "offset": 3
        },
        {
          "name": "ER",
          "tag_type": "atomic",
          "data_type_name": "BOOL",
          "bit": 3,
          "offset": 3
        },
        {
          "name": "UL",
          "tag_type": "atomic",
          "data_type_name": "BOOL",
          "bit": 2,
          "offset": 3
        },
        {
          "name": "IN",
          "tag_type": "atomic",
          "data_type_name": "BOOL",
          "bit": 1,
          "offset": 3
        },
        {
          "name": "FD",
          "tag_type": "atomic",
          "data_type_name": "BOOL",
          "bit": 0,
          "offset": 3
        }
      ]
    },
    {
      "name": "MOTION_INSTRUCTION",
      "fields": [
        {
          "name": "FLAGS",
          "tag_type": "atomic",
          "data_type_name": "DINT",
          "offset": 0
        },
        {
          "name": "EN",
          "tag_type": "atomic",
          "data_type_name": "BOOL",
          "bit": 7,
          "offset": 3
        },
        {
          "name": "DN",
          "tag_type": "atomic",
          "data_type_name": "BOOL",
          "bit": 5,
          "offset": 3
        },
        {
          "name": "ER",
          "tag_type": "atomic",
          "data_type_name": "BOOL",
          "bit": 4,
          "offset": 3
        },
        {
          "name": "PC",
          "tag_type": "atomic",
          "data_type_name": "BOOL",
          "bit": 3,
          "offset": 3
        },
        {
          "name": "IP",
          "tag_type": "atomic",
          "data_type_name": "BOOL",
          "bit": 2,
          "offset": 3
        },
        {
          "name": "AC",
          "tag_type": "atomic",
          "data_type_name": "BOOL",
          "bit": 7,
          "offset": 2
        },
        {
          "name": "ACCEL",
          "tag_type": "atomic",
          "data_type_name": "BOOL",
          "bit": 0,
          "offset": 0
        },
        {
          "name": "DECEL",
          "tag_type": "atomic",
          "data_type_name": "BOOL",
          "bit": 1,
          "offset": 0
        },
        {
          "name": "TrackingMaster",
          "tag_type": "atomic",
          "data_type_name": "BOOL",
          "bit": 2,
          "offset": 0
        },
        {
          "name": "CalculatedDataAvailable",
          "tag_type": "atomic",
          "data_type_name": "BOOL",
          "bit": 3,
          "offset": 0
        },
        {
          "name": "ERR",
          "tag_type": "atomic",
          "data_type_name": "INT",
          "offset": 4
        },
        {
          "name": "STATUS",
          "tag_type": "atomic",
          "data_type_name": "SINT",
          "offset": 6
        },
        {
          "name": "STATE",
          "tag_type": "atomic",
          "data_type_name": "SINT",
          "offset": 7
        },
        {
          "name": "SEGMENT",
          "tag_type": "atomic",
          "data_type_name": "DINT",
          "offset": 8
        },
        {
          "name": "EXERR",
          "tag_type": "atomic",
          "data_type_name": "SINT",
          "offset": 12
        },
        {
          "name": "DEAD_ZONE1",
          "tag_type": "atomic",
          "data_type_name": "SINT",
          "offset": 13
        },
        {
          "name": "DEAD_ZONE2",
          "tag_type": "atomic",
          "data_type_name": "SINT",
          "offset": 14
        },
        {
          "name": "DEAD_ZONE3",
          "tag_type": "atomic",
          "data_type_name": "SINT",
          "offset": 15
        }
      ]
    },
    {
      "name": "TIMER",
      "fields": [
        {
          "name": "PRE",
          "tag_type": "atomic",
          "data_type_name": "DINT",
          "offset": 4
        },
        {
          "name": "ACC",
          "tag_type": "atomic",
          "data_type_name": "DINT",
          "offset": 8
        },
        {
          "name": "EN",
          "tag_type": "atomic",
          "data_type_name": "BOOL",
          "bit": 7,
          "offset": 3
        },
        {
          "name": "TT",
          "tag_type": "atomic",
          "data_type_name": "BOOL",
          "bit": 6,
          "offset": 3
        },
        {
          "name": "DN",
          "tag_type": "atomic",
          "data_type_name": "BOOL",
          "bit": 5,
          "offset": 3
        }
      ]
    }
  ],
  "program_tags": [
    {
      "name": "Cam_F_InspectionRes_0",
      "fully_qualified_name": "Program:Camera.Cam_F_InspectionRes_0",
      "tag_type": "atomic",
      "data_type_name": "REAL",
      "alias": false,
      "external_access": "Read Only",
      "dimensions": [
        32,
        0,
        0
      ],
      "array_dimensions": 1,
      "program": "Camera"
    },
    {
      "name": "Cam_F_InspectionRes_1",
      "fully_qualified_name": "Program:Camera.Cam_F_InspectionRes_1",
      "tag_type": "atomic",
      "data_type_name": "REAL",
      "alias": false,
      "external_access": "Read Only",
      "dimensions": [
        10,
        0,
        0
      ],
      "array_dimensions": 1,
      "program": "Camera"
    },
    {
      "name": "Cam_F_InspectionRes_2",
      "fully_qualified_name": "Program:Camera.Cam_F_InspectionRes_2",
      "tag_type": "atomic",
      "data_type_name": "REAL",
      "alias": false,
      "external_access": "Read Only",
      "dimensions": [
        10,
        0,
        0
      ],
      "array_dimensions": 1,
      "program": "Camera"
    },
    {
      "name": "Cam_F_InspectionRes_3",
      "fully_qualified_name": "Program:Camera.Cam_F_InspectionRes_3",
      "tag_type": "atomic",
      "data_type_name": "REAL",
      "alias": false,
      "external_access": "Read Only",
      "dimensions": [
        10,
        0,
        0
      ],
      "array_dimensions": 1,
      "program": "Camera"
    },
    {
      "name": "FIFO_CTRL",
      "fully_qualified_name": "Program:Camera.FIFO_CTRL",
      "tag_type": "struct",
      "data_type_name": "CONTROL",
      "alias": false,
      "external_access": "Read Only",
      "dimensions": [
        6,
        0,
        0
      ],
      "array_dimensions": 1,
      "program": "Camera",
      "udt_name": "CONTROL"
    },
    {
      "name": "foundIt",
      "fully_qualified_name": "Program:Camera.foundIt",
      "tag_type": "atomic",
      "data_type_name": "BOOL",
      "alias": false,
      "external_access": "Read Only",
      "dimensions": [
        0,
        0,
        0
      ],
      "array_dimensions": 0,
      "program": "Camera",
      "bit_position": 0
    },
    {
      "name": "LightRing",
      "fully_qualified_name": "Program:Camera.LightRing",
      "tag_type": "struct",
      "data_type_name": "TIMER",
      "alias": false,
      "external_access": "Read Only",
      "dimensions": [
        0,
        0,
        0
      ],
      "array_dimensions": 0,
      "program": "Camera",
      "udt_name": "TIMER"
    },
    {
      "name": "Manual_Trig",
      "fully_qualified_name": "Program:Camera.Manual_Trig",
      "tag_type": "atomic",
      "data_type_name": "BOOL",
      "alias": false,
      "external_access": "Read Only",
      "dimensions": [
        0,
        0,
        0
      ],
      "array_dimensions": 0,
      "program": "Camera",
      "bit_position": 0
    },
    {
      "name": "osob",
      "fully_qualified_name": "Program:Camera.osob",
      "tag_type": "atomic",
      "data_type_name": "DWORD",
      "alias": false,
      "external_access": "Read Only",
      "dimensions": [
        1,
        0,
        0
      ],
      "array_dimensions": 1,
      "program": "Camera"
    },
    {
      "name": "ossb",
      "fully_qualified_name": "Program:Camera.ossb",
      "tag_type": "atomic",
      "data_type_name": "DWORD",
      "alias": false,
      "external_access": "Read Only",
      "dimensions": [
        1,
        0,
        0
      ],
      "array_dimensions": 1,
      "program": "Camera"
    },
    {
      "name": "Pos_trigger",
      "fully_qualified_name": "Program:Camera.Pos_trigger",
      "tag_type": "atomic",
      "data_type_name": "BOOL",
      "alias": false,
      "external_access": "Read Only",
      "dimensions": [
        0,
        0,
        0
      ],
      "array_dimensions": 0,
      "program": "Camera",
      "bit_position": 0
    },
    {
      "name": "RegistrationData",
      "fully_qualified_name": "Program:Camera.RegistrationData",
      "tag_type": "struct",
      "data_type_name": "MOTION_INSTRUCTION",
      "alias": false,
      "external_access": "Read Only",
      "dimensions": [
        8,
        0,
        0
      ],
      "array_dimensions": 1,
      "program": "Camera",
      "udt_name": "MOTION_INSTRUCTION"
    },
    {
      "name": "triggerOneShotOB",
      "fully_qualified_name": "Program:Camera.triggerOneShotOB",
      "tag_type": "atomic",
      "data_type_name": "BOOL",
      "alias": false,
      "external_access": "Read Only",
      "dimensions": [
        0,
        0,
        0
      ],
      "array_dimensions": 0,
      "program": "Camera",
      "bit_position": 0
    },
    {
      "name": "triggerOneShotSB",
      "fully_qualified_name": "Program:Camera.triggerOneShotSB",
      "tag_type": "atomic",
      "data_type_name": "BOOL",
      "alias": false,
      "external_access": "Read Only",
      "dimensions": [
        0,
        0,
        0
      ],
      "array_dimensions": 0,
      "program": "Camera",
      "bit_position": 0
    },
    {
      "name": "TriggerResetTimer1",
      "fully_qualified_name": "Program:Camera.TriggerResetTimer1",
      "tag_type": "struct",
      "data_type_name": "TIMER",
      "alias": false,
      "external_access": "Read Only",
      "dimensions": [
        0,
        0,
        0
      ],
      "array_dimensions": 0,
      "program": "Camera",
      "udt_name": "TIMER"
    },
    {
      "name": "TriggerResetTimer2",
      "fully_qualified_name": "Program:Camera.TriggerResetTimer2",
      "tag_type": "struct",
      "data_type_name": "TIMER",
      "alias": false,
      "external_access": "Read Only",
      "dimensions": [
        0,
        0,
        0
      ],
      "array_dimensions": 0,
      "program": "Camera",
      "udt_name": "TIMER"
    },
    {
      "name": "X_axis_Cam_F_Pos",
      "fully_qualified_name": "Program:Camera.X_axis_Cam_F_Pos",
      "tag_type": "atomic",
      "data_type_name": "REAL",
      "alias": false,
      "external_access": "Read Only",
      "dimensions": [
        10,
        0,
        0
      ],
      "array_dimensions": 1,
      "program": "Camera"
    },
    {
      "name": "X_axis_Cam_F_Position",
      "fully_qualified_name": "Program:Camera.X_axis_Cam_F_Position",
      "tag_type": "atomic",
      "data_type_name": "REAL",
      "alias": false,
      "external_access": "Read Only",
      "dimensions": [
        0,
        0,
        0
      ],
      "array_dimensions": 0,
      "program": "Camera"
    },
    {
      "name": "x_pos",
      "fully_qualified_name": "Program:Camera.x_pos",
      "tag_type": "atomic",
      "data_type_name": "REAL",
      "alias": false,
      "external_access": "Read Only",
      "dimensions": [
        0,
        0,
        0
      ],
      "array_dimensions": 0,
      "program": "Camera"
    },
    {
      "name": "x_pos_next",
      "fully_qualified_name": "Program:Camera.x_pos_next",
      "tag_type": "atomic",
      "data_type_name": "REAL",
      "alias": false,
      "external_access": "Read/Write",
      "dimensions": [
        0,
        0,
        0
      ],
      "array_dimensions": 0,
      "program": "Camera"
    },
    {
      "name": "Y_axis_Cam_F_Pos",
      "fully_qualified_name": "Program:Camera.Y_axis_Cam_F_Pos",
      "tag_type": "atomic",
      "data_type_name": "REAL",
      "alias": false,
      "external_access": "Read Only",
      "dimensions": [
        10,
        0,
        0
      ],
      "array_dimensions": 1,
      "program": "Camera"
    },
    {
      "name": "Y_axis_Cam_F_Position",
      "fully_qualified_name": "Program:Camera.Y_axis_Cam_F_Position",
      "tag_type": "atomic",
      "data_type_name": "REAL",
      "alias": false,
      "external_access": "Read Only",
      "dimensions": [
        0,
        0,
        0
      ],
      "array_dimensions": 0,
      "program": "Camera"
    },
    {
      "name": "y_pos",
      "fully_qualified_name": "Program:Camera.y_pos",
      "tag_type": "atomic",
      "data_type_name": "REAL",
      "alias": false,
      "external_access": "Read/Write",
      "dimensions": [
        0,
        0,
        0
      ],
      "array_dimensions": 0,
      "program": "Camera"
    },
    {
      "name": "y_pos_next",
      "fully_qualified_name": "Program:Camera.y_pos_next",
      "tag_type": "atomic",
      "data_type_name": "REAL",
      "alias": false,
      "external_access": "Read/Write",
      "dimensions": [
        0,
        0,
        0
      ],
      "array_dimensions": 0,
      "program": "Camera"
    }
  ]
}
